muffin_databases/__init__.py
muffin_databases/py.typed
muffin_databases-0.6.2.dist-info/LICENSE
muffin_databases-0.6.2.dist-info/METADATA
muffin_databases-0.6.2.dist-info/WHEEL
muffin_databases-0.6.2.dist-info/RECORD
