Metadata-Version: 2.1
Name: muffin-databases
Version: 0.6.2
Summary: Async support for a range of databases
Home-page: https://github.com/klen/muffin-databases
License: MIT
Keywords: sql,postgres,mysql,sqlite,asyncio,asgi,web,muffin
Author: Kirill Klenov
Author-email: horneds@gmail.com
Requires-Python: >=3.9,<4.0
Classifier: Development Status :: 5 - Production/Stable
Classifier: Framework :: AsyncIO
Classifier: Intended Audience :: Developers
Classifier: License :: OSI Approved :: MIT License
Classifier: Programming Language :: Python
Classifier: Programming Language :: Python :: 3
Classifier: Programming Language :: Python :: 3.9
Classifier: Programming Language :: Python :: 3.10
Classifier: Programming Language :: Python :: 3.11
Classifier: Programming Language :: Python :: 3.12
Classifier: Programming Language :: Python :: 3.13
Classifier: Topic :: Internet :: WWW/HTTP
Provides-Extra: mysql
Provides-Extra: postgres
Provides-Extra: sqlite
Requires-Dist: aiomysql ; extra == "mysql"
Requires-Dist: aiosqlite ; extra == "sqlite"
Requires-Dist: asyncpg ; extra == "postgres"
Requires-Dist: databases
Requires-Dist: muffin
Project-URL: Repository, https://github.com/klen/muffin-databases
